conifer/__init__.py
conifer/model.py
conifer/backends/__init__.py
conifer/backends/common.py
conifer/backends/boards/__init__.py
conifer/backends/boards/boards.py
conifer/backends/boards/configs/alveo/xilinx_u200_gen3x16_xdma_2_202110_1.json
conifer/backends/boards/configs/zynq/kr260.json
conifer/backends/boards/configs/zynq/kv260.json
conifer/backends/boards/configs/zynq/pynq_z2.json
conifer/backends/boards/configs/zynq/ultra96v2.json
conifer/backends/boards/configs/zynq/zcu102.json
conifer/backends/boards/configs/zynq/zcu104.json
conifer/backends/boards/src/LICENSE
conifer/backends/boards/src/build_bit.tcl
conifer/backends/cpp/__init__.py
conifer/backends/cpp/writer.py
conifer/backends/cpp/include/conifer.h
conifer/backends/cpp/template/bridge.cpp
conifer/backends/fpu/__init__.py
conifer/backends/fpu/runtime.py
conifer/backends/fpu/writer.py
conifer/backends/fpu/src/LICENSE
conifer/backends/fpu/src/README.md
conifer/backends/fpu/src/build_hls.tcl
conifer/backends/fpu/src/changes.txt
conifer/backends/fpu/src/fpu.cpp
conifer/backends/fpu/src/fpu.h
conifer/backends/vhdl/__init__.py
conifer/backends/vhdl/simulators.py
conifer/backends/vhdl/writer.py
conifer/backends/vhdl/firmware/AddReduce.vhd
conifer/backends/vhdl/firmware/BDT.vhd
conifer/backends/vhdl/firmware/BDTTestbench.vhd
conifer/backends/vhdl/firmware/BDTTop.vhd
conifer/backends/vhdl/firmware/Constants.vhd
conifer/backends/vhdl/firmware/SimulationInput.vhd
conifer/backends/vhdl/firmware/SimulationOutput.vhd
conifer/backends/vhdl/firmware/Split.vhd
conifer/backends/vhdl/firmware/TestUtil.vhd
conifer/backends/vhdl/firmware/Tree.vhd
conifer/backends/vhdl/firmware/Types.vhd
conifer/backends/vhdl/scripts/ghdl_compile.sh
conifer/backends/vhdl/scripts/modelsim_compile.sh
conifer/backends/vhdl/scripts/synth.tcl
conifer/backends/vhdl/scripts/xsim_compile.sh
conifer/backends/xilinxhls/__init__.py
conifer/backends/xilinxhls/runtime.py
conifer/backends/xilinxhls/writer.py
conifer/backends/xilinxhls/firmware/BDT_rolled.h
conifer-1.7.dist-info/licenses/LICENSE
conifer-1.7.dist-info/METADATA
conifer-1.7.dist-info/WHEEL
conifer-1.7.dist-info/top_level.txt
conifer-1.7.dist-info/RECORD
