Metadata-Version: 2.4
Name: conifer
Version: 1.7
Summary: BDT Inference for FPGAs
Home-page: https://github.com/thesps/conifer
Author: Sioni Summers
Author-email: sioni@cern.ch
Classifier: Programming Language :: Python :: 3
Requires-Python: >=3.8
License-File: LICENSE
Requires-Dist: numpy
Requires-Dist: pybind11
Requires-Dist: packaging
Dynamic: author
Dynamic: author-email
Dynamic: classifier
Dynamic: description
Dynamic: description-content-type
Dynamic: home-page
Dynamic: license-file
Dynamic: requires-dist
Dynamic: requires-python
Dynamic: summary
